qfi_opt/__init__.py
qfi_opt/dissipation.py
qfi_opt/examples/__init__.py
qfi_opt/examples/benchmark_opt_methods.py
qfi_opt/examples/calculate_qfi.py
qfi_opt/examples/matt_benchmark.py
qfi_opt/examples/plot_kink.py
qfi_opt/examples/plot_qfi_over_space.py
qfi_opt/examples/plot_spin_state.py
qfi_opt/plot.py
qfi_opt/spin_models.py
qfi_opt/spin_models_test.py
qfi_opt-0.0.3.dist-info/LICENSE
qfi_opt-0.0.3.dist-info/METADATA
qfi_opt-0.0.3.dist-info/WHEEL
qfi_opt-0.0.3.dist-info/RECORD
